README.md
setup.py
SymSim/__init__.py
SymSim.egg-info/PKG-INFO
SymSim.egg-info/SOURCES.txt
SymSim.egg-info/dependency_links.txt
SymSim.egg-info/not-zip-safe
SymSim.egg-info/requires.txt
SymSim.egg-info/top_level.txt
SymSim/draw/__init__.py
SymSim/sim/__init__.py
SymSim/sim/cluster.py
SymSim/sim/clusters.py
SymSim/sim/shape_function.py
SymSim/sim/simulation_cube.py
SymSim/utils/__init__.py
SymSim/utils/rotation_utils.py
SymSim/utils/simulation_utils.py
SymSim/utils/vector_utils.py