Metadata-Version: 1.0
Name: SymSim
Version: 0.1
Summary: Tool for simulating planes of symmetries assuming kinematic diffraction
Home-page: https://github.com/CSSFrancis/SymSim
Author: CSSFrancis
Author-email: csfrancis@wisc.edu
License: UNKNOWN
Keywords: Simulations STEM Electron Microscopy Glass
Platform: UNKNOWN
